py_pdf_parser/__init__.py
py_pdf_parser/common.py
py_pdf_parser/components.py
py_pdf_parser/exceptions.py
py_pdf_parser/filtering.py
py_pdf_parser/loaders.py
py_pdf_parser/sectioning.py
py_pdf_parser/tables.py
py_pdf_parser/visualise/__init__.py
py_pdf_parser/visualise/background.py
py_pdf_parser/visualise/info_figure.py
py_pdf_parser/visualise/main.py
py_pdf_parser/visualise/sections.py
py_pdf_parser-0.13.0.dist-info/LICENSE
py_pdf_parser-0.13.0.dist-info/METADATA
py_pdf_parser-0.13.0.dist-info/WHEEL
py_pdf_parser-0.13.0.dist-info/top_level.txt
py_pdf_parser-0.13.0.dist-info/RECORD
